VL53L1X.py
VL53L1X2.py
vl53l1x_python.cpython-36m-arm-linux-gnueabihf.so
VL53L1X2-0.1.5.dist-info/METADATA
VL53L1X2-0.1.5.dist-info/WHEEL
VL53L1X2-0.1.5.dist-info/top_level.txt
VL53L1X2-0.1.5.dist-info/RECORD
