Metadata-Version: 2.1
Name: VL53L1X2
Version: 0.1.5
Summary: vl53l1x distance sensor driver for Raspberry Pi
Home-page: https://github.com/josemotta/vl53l1x-python
Maintainer: Phil Howard/Nagy Attila/Jose Motta
Maintainer-email: phil@pimoroni.com
License: UNKNOWN
Platform: UNKNOWN
Requires: smbus2
Requires-Dist: smbus2
